vcdb-0.1.dist-info/top_level.txt
vcdb-0.1.dist-info/RECORD
vcdb-0.1.dist-info/WHEEL
vcdb-0.1.dist-info/DESCRIPTION.rst
vcdb-0.1.dist-info/metadata.json
vcdb-0.1.dist-info/METADATA
vcdb-0.1.dist-info/entry_points.txt
vcdb/common.py
vcdb/subversion.py
vcdb/__init__.py
vcdb/command.py
