Metadata-Version: 2.0
Name: vcdb
Version: 0.1
Summary: build SQL database from version control repository
Home-page: https://github.com/roskakori/vcdb
Author: Thomas Aglassinger
Author-email: roskakori@users.sourceforge.net
License: LGPLv3+
Keywords: version control repository vcs database query
Platform: UNKNOWN
Classifier: Development Status :: 3 - Alpha
Classifier: Intended Audience :: Developers
Classifier: Topic :: Software Development
Classifier: License :: OSI Approved :: GNU Lesser General Public License v3 or later (LGPLv3+)
Classifier: Programming Language :: Python :: 3
Classifier: Programming Language :: Python :: 3.4
Classifier: Programming Language :: Python :: 3.5
Requires-Dist: sqlalchemy (>=0.8.4)
